my_little_helpers/__init__.py
my_little_helpers/db_helpers.py
my_little_helpers/df_helpers.py
my_little_helpers/quarter_helpers.py
my_little_helpers/visualization_helpers.py
my_little_helpers_frechfrechfrech-0.1.dist-info/LICENSE
my_little_helpers_frechfrechfrech-0.1.dist-info/METADATA
my_little_helpers_frechfrechfrech-0.1.dist-info/WHEEL
my_little_helpers_frechfrechfrech-0.1.dist-info/top_level.txt
my_little_helpers_frechfrechfrech-0.1.dist-info/RECORD
