Metadata-Version: 2.1
Name: my-little-helpers-frechfrechfrech
Version: 0.1
Summary: Functions that I use often
Home-page: https://github.com/frechfrechfrech/helper_functions
Author: Alex Frech
Author-email: frechfrechfrech@gmail.com
License: MIT
Platform: UNKNOWN
Classifier: Programming Language :: Python :: 3
Classifier: License :: OSI Approved :: MIT License
Classifier: Operating System :: OS Independent
Requires-Dist: pandas (==0.23.4)
Requires-Dist: numpy (==1.14.3)
Requires-Dist: psycopg2 (==2.7.5)
Requires-Dist: mysqlclient (==1.3.14)
Requires-Dist: matplotlib (==2.2.2)
Requires-Dist: seaborn (==0.9.0)
